{
  "_id": "2a939f2399fb1f01",
  "name": "Armalite 44",
  "type": "weapon",
  "img": "icons/weapons/guns/gun-pistol.webp",
  "system": {
    "category": "pistol",
    "skill": "firearms",
    "damage_power": 9,
    "damage_level": "M",
    "damage_code": "9M",
    "concealability": 4,
    "ammo_type": "regular",
    "ammo_capacity": 0,
    "reach": 0,
    "weight": 2.25,
    "cost": 450,
    "availability": "4/24hrs",
    "street_index": 1,
    "legality": "",
    "description": ""
  },
  "folder": null,
  "flags": {},
  "_stats": {
    "systemId": "shadowrun2e"
  }
}