{
  "_id": "637effbaa585f662",
  "name": "Beretta 100S Smart",
  "type": "weapon",
  "img": "icons/weapons/guns/gun-pistol.webp",
  "system": {
    "category": "pistol",
    "skill": "firearms",
    "damage_power": 9,
    "damage_level": "M",
    "damage_code": "9M",
    "concealability": 5,
    "ammo_type": "regular",
    "ammo_capacity": 0,
    "reach": 0,
    "weight": 2.5,
    "cost": 1300,
    "availability": "5/36hrs",
    "street_index": 1.5,
    "legality": "",
    "description": ""
  },
  "folder": null,
  "flags": {},
  "_stats": {
    "systemId": "shadowrun2e"
  }
}