{
  "_id": "0f766df738c1d861",
  "name": "Bug Detector Lvl 2",
  "type": "cyberware",
  "img": "icons/equipment/head/helm-visor-technological.webp",
  "system": {
    "grade": {
      "label": "Standard",
      "mult": 1,
      "costMult": 1
    },
    "essence_cost": 0.15,
    "installed": false,
    "category": "bodyware",
    "cost": 25000,
    "availability": "",
    "street_index": 1.75,
    "mods": {},
    "description": ""
  },
  "folder": null,
  "flags": {},
  "_stats": {
    "systemId": "shadowrun2e"
  }
}