{
  "_id": "565b83ac2bc1660c",
  "name": "Bug Detector Lvl 3 (Betaware)",
  "type": "cyberware",
  "img": "icons/equipment/head/helm-visor-technological.webp",
  "system": {
    "grade": {
      "label": "Betaware",
      "mult": 0.6,
      "costMult": 5
    },
    "essence_cost": 0.12,
    "installed": false,
    "category": "bodyware",
    "cost": 187500,
    "availability": "",
    "street_index": 1.75,
    "mods": {},
    "description": ""
  },
  "folder": null,
  "flags": {},
  "_stats": {
    "systemId": "shadowrun2e"
  }
}