{
  "_id": "8282a5edab5cef20",
  "name": "Mead Electronic Notebook 30 Mp",
  "type": "gear",
  "img": "icons/containers/bags/pack-simple.webp",
  "system": {
    "category": "lifestyle",
    "subcategory": "",
    "rating": 0,
    "quantity": 1,
    "concealability": 0,
    "weight": 1,
    "cost": 3000,
    "availability": "always",
    "street_index": 1,
    "legality": "",
    "description": "Mead Electronic Notebook 30 Mp - Lifestyle"
  },
  "folder": null,
  "flags": {},
  "_stats": {
    "systemId": "shadowrun2e"
  }
}