{
  "_id": "9de01dba0d84ee39",
  "name": "Radio Scrambler Level 9",
  "type": "gear",
  "img": "icons/containers/bags/pack-simple.webp",
  "system": {
    "category": "misc",
    "subcategory": "",
    "rating": 9,
    "quantity": 1,
    "concealability": 0,
    "weight": null,
    "cost": 27000,
    "availability": "6/36hrs",
    "street_index": 1.5,
    "legality": "",
    "description": "Radio Scrambler Level 9 - Stuff With Ratings"
  },
  "folder": null,
  "flags": {},
  "_stats": {
    "systemId": "shadowrun2e"
  }
}