{
  "_id": "fc4402b786a07730",
  "name": "Tracking Signal Lv 2",
  "type": "gear",
  "img": "icons/containers/bags/pack-simple.webp",
  "system": {
    "category": "security",
    "subcategory": "",
    "rating": 0,
    "quantity": 1,
    "concealability": 0,
    "weight": null,
    "cost": 400,
    "availability": "2/72hrs",
    "street_index": 2,
    "legality": "",
    "description": "Tracking Signal Lv 2 - Surveillance and Security"
  },
  "folder": null,
  "flags": {},
  "_stats": {
    "systemId": "shadowrun2e"
  }
}