{
  "_id": "b6787ddd58472da9",
  "name": "White Noise Generator Lv 2",
  "type": "gear",
  "img": "icons/containers/bags/pack-simple.webp",
  "system": {
    "category": "misc",
    "subcategory": "",
    "rating": 2,
    "quantity": 1,
    "concealability": 0,
    "weight": 1,
    "cost": 3000,
    "availability": "2/72hrs",
    "street_index": 1.5,
    "legality": "",
    "description": "White Noise Generator Lv 2 - Stuff With Ratings"
  },
  "folder": null,
  "flags": {},
  "_stats": {
    "systemId": "shadowrun2e"
  }
}